README.md
setup.py
kmux_mongo/__init__.py
kmux_mongo/kmux_model.py
kmux_mongo/kmux_mongo.py
kmux_mongo.egg-info/PKG-INFO
kmux_mongo.egg-info/SOURCES.txt
kmux_mongo.egg-info/dependency_links.txt
kmux_mongo.egg-info/requires.txt
kmux_mongo.egg-info/top_level.txt