Metadata-Version: 2.1
Name: kmux-mongo
Version: 0.0.2
Summary: mongo client
Home-page: https://gitee.com/muxiaofei/kmux-mongo
Author: Mu Xiaofei
Author-email: me@muxiaofei.cn
License: UNKNOWN
Keywords: mongo
Platform: UNKNOWN
Classifier: Programming Language :: Python :: 3
Classifier: License :: OSI Approved :: MIT License
Classifier: Operating System :: OS Independent
